setup.py
bin/programaker-unix-bridge
plaza_unix_service/config.py
plaza_unix_service/monitor_manager.py
programaker_unix_bridge.egg-info/PKG-INFO
programaker_unix_bridge.egg-info/SOURCES.txt
programaker_unix_bridge.egg-info/dependency_links.txt
programaker_unix_bridge.egg-info/not-zip-safe
programaker_unix_bridge.egg-info/requires.txt
programaker_unix_bridge.egg-info/top_level.txt