Metadata-Version: 1.1
Name: programaker-unix-bridge
Version: 0.0.1.post3
Summary: Unix-like abstraction to create Programaker bridges.
Home-page: UNKNOWN
Author: kenkeiras
Author-email: kenkeiras@codigoparallevar.com
License: Apache License 2.0
Platform: UNKNOWN
Classifier: Programming Language :: Python :: 3
Classifier: License :: OSI Approved :: Apache Software License
Classifier: Development Status :: 2 - Pre-Alpha
Classifier: Intended Audience :: Developers
